{
  "unpublishedPage": {
    "name": "new-blank-page",
    "slug": "new-blank-page",
    "layouts": [
      {
        "viewMode": false,
        "dsl": {
          "widgetName": "MainContainer",
          "backgroundColor": "none",
          "rightColumn": 1224,
          "snapColumns": 64,
          "detachFromLayout": true,
          "widgetId": "0",
          "topRow": 0,
          "bottomRow": 498.00000000000006,
          "containerStyle": "none",
          "snapRows": 123,
          "parentRowSpace": 1,
          "type": "CANVAS_WIDGET",
          "canExtend": true,
          "version": 88,
          "minHeight": 1250,
          "useAutoLayout": true,
          "parentColumnSpace": 1,
          "responsiveBehavior": "fill",
          "dynamicBindingPathList": [],
          "leftColumn": 0,
          "positioning": "vertical",
          "flexLayers": [
            {
              "children": [
                {
                  "id": "0xpqf0ga8b",
                  "align": "start"
                }
              ]
            },
            {
              "children": [
                {
                  "id": "bte3xcjs16",
                  "align": "start"
                }
              ]
            }
          ]
        },
        "layoutOnLoadActions": [
          [
            {
              "id": "new-blank-page_Select_public_users1",
              "name": "Select_public_users1",
              "confirmBeforeExecute": false,
              "pluginType": "DB",
              "jsonPathKeys": [
                "Table1.searchText",
                "Table1.sortOrder.order !== \"desc\" ? \"\" : \"DESC\"",
                "Table1.sortOrder.column || 'id'",
                "Table1.pageSize",
                "Table1.pageOffset"
              ],
              "timeoutInMillisecond": 10000
            }
          ],
          [
            {
              "id": "new-blank-page_Total_record_public_users1",
              "name": "Total_record_public_users1",
              "confirmBeforeExecute": false,
              "pluginType": "DB",
              "jsonPathKeys": [
                "Table1.searchText"
              ],
              "timeoutInMillisecond": 10000
            }
          ]
        ],
        "layoutOnLoadActionErrors": [],
        "validOnPageLoadActions": true,
        "id": "new-blank-page",
        "deleted": false,
        "policies": [],
        "userPermissions": []
      }
    ],
    "userPermissions": [],
    "policies": [],
    "isHidden": false
  },
  "deleted": false,
  "gitSyncId": "65c0e2780df1051637662a21_65c0e37e0df1051637662a73"
}